README.rst
setup.py
kazoo/__init__.py
kazoo/client.py
kazoo/exceptions.py
kazoo/request_objects.py
kazoo/rest_resources.py
kazoo_api.egg-info/PKG-INFO
kazoo_api.egg-info/SOURCES.txt
kazoo_api.egg-info/dependency_links.txt
kazoo_api.egg-info/requires.txt
kazoo_api.egg-info/top_level.txt