Metadata-Version: 1.0
Name: kazoo-api
Version: 0.1.3
Summary: Wrapper for the Kazoo API
Home-page: http://2600hz.com/platform.html
Author: Alex Good
Author-email: UNKNOWN
License: MIT License
Platform: UNKNOWN
